sdrf_pipelines/__init__.py
sdrf_pipelines/parse_sdrf.py
sdrf_pipelines/maxquant/__init__.py
sdrf_pipelines/maxquant/maxquant.py
sdrf_pipelines/maxquant/modifications.xml
sdrf_pipelines/maxquant/param2sdrf.yml
sdrf_pipelines/msstats/__init__.py
sdrf_pipelines/msstats/msstats.py
sdrf_pipelines/normalyzerde/__init__.py
sdrf_pipelines/normalyzerde/normalyzerde.py
sdrf_pipelines/ols/__init__.py
sdrf_pipelines/ols/bto.parquet
sdrf_pipelines/ols/chebi.parquet
sdrf_pipelines/ols/cl.parquet
sdrf_pipelines/ols/clo.parquet
sdrf_pipelines/ols/efo.parquet
sdrf_pipelines/ols/mondo.parquet
sdrf_pipelines/ols/ncbitaxon.parquet
sdrf_pipelines/ols/ncit.parquet
sdrf_pipelines/ols/ols.py
sdrf_pipelines/ols/pato.parquet
sdrf_pipelines/ols/pride.parquet
sdrf_pipelines/ols/psi-ms.parquet
sdrf_pipelines/ols/uberon.parquet
sdrf_pipelines/ols/unimod.parquet
sdrf_pipelines/openms/__init__.py
sdrf_pipelines/openms/openms.py
sdrf_pipelines/openms/unimod.py
sdrf_pipelines/openms/unimod.xml
sdrf_pipelines/sdrf/__init__.py
sdrf_pipelines/sdrf/sdrf.py
sdrf_pipelines/sdrf/sdrf_schema.py
sdrf_pipelines/sdrf_merge/param2sdrf.yml
sdrf_pipelines/utils/__init__.py
sdrf_pipelines/utils/exceptions.py
sdrf_pipelines-0.0.32.data/data/LICENSE
sdrf_pipelines-0.0.32.data/data/param2sdrf.yml
sdrf_pipelines-0.0.32.data/data/unimod.xml
sdrf_pipelines-0.0.32.dist-info/licenses/LICENSE
tests/__init__.py
tests/conftest.py
tests/helpers.py
tests/test_convert_openms.py
tests/test_ontology.py
tests/test_openms.py
tests/test_sdrfchecker.py
tests/test_unimod.py
sdrf_pipelines-0.0.32.dist-info/METADATA
sdrf_pipelines-0.0.32.dist-info/WHEEL
sdrf_pipelines-0.0.32.dist-info/entry_points.txt
sdrf_pipelines-0.0.32.dist-info/top_level.txt
sdrf_pipelines-0.0.32.dist-info/RECORD
