Metadata-Version: 2.4
Name: sdrf-pipelines
Version: 0.0.32
Summary: Translate, convert SDRF to configuration pipelines
Home-page: https://github.com/bigbio/sdrf-pipelines
Author: BigBio Team
Author-email: ypriverol@gmail.com
License: 'Apache 2.0
Keywords: sdrf python multiomics proteomics
Platform: any
Classifier: Programming Language :: Python :: 3
Classifier: License :: OSI Approved :: Apache Software License
Classifier: Operating System :: OS Independent
Classifier: Topic :: Scientific/Engineering :: Bio-Informatics
Requires-Python: >=3.8
License-File: LICENSE
Requires-Dist: click
Requires-Dist: pandas
Requires-Dist: pandas_schema
Requires-Dist: requests
Requires-Dist: pytest
Requires-Dist: pyyaml
Requires-Dist: defusedxml
Requires-Dist: pyarrow
Requires-Dist: duckdb
Requires-Dist: rdflib
Requires-Dist: setuptools
Dynamic: author
Dynamic: author-email
Dynamic: classifier
Dynamic: description
Dynamic: description-content-type
Dynamic: home-page
Dynamic: keywords
Dynamic: license
Dynamic: license-file
Dynamic: platform
Dynamic: requires-dist
Dynamic: requires-python
Dynamic: summary
